NeXov/cli.py
NeXov/core.py
NeXov/tokenizer.py
nexov-1.1.1.dist-info/licenses/LICENSE
nexov-1.1.1.dist-info/METADATA
nexov-1.1.1.dist-info/WHEEL
nexov-1.1.1.dist-info/entry_points.txt
nexov-1.1.1.dist-info/top_level.txt
nexov-1.1.1.dist-info/RECORD
