Metadata-Version: 2.4
Name: NeXov
Version: 1.1.1
Summary: NeXov Enables eXtensible Observation of Vertices
Author-email: Kurimochi <kurimochi.sec@gmail.com>
License: MIT License
Project-URL: Homepage, https://github.com/kurimochi/NeXov
Project-URL: Bug Tracker, https://github.com/kurimochi/NeXov/issues
Classifier: Programming Language :: Python :: 3
Classifier: License :: OSI Approved :: MIT License
Classifier: Operating System :: OS Independent
Requires-Python: >=3.10
License-File: LICENSE
Requires-Dist: networkx
Requires-Dist: mecab-python3
Requires-Dist: matplotlib
Requires-Dist: graphviz
Dynamic: license-file
